mfhm/__init__.py
mfhm/center.py
mfhm/errors.py
mfhm/log.py
mfhm/metadata.py
mfhm/proxy.py
mfhm/service.py
mfhm/utils.py
mfhm/wrapper.py
mfhm-0.1.1.dist-info/LICENSE
mfhm-0.1.1.dist-info/WHEEL
mfhm-0.1.1.dist-info/METADATA
mfhm-0.1.1.dist-info/RECORD
