Metadata-Version: 2.1
Name: mfhm
Version: 0.1.1
Summary: HTTP microservice package based on FastAPI and HTTPX
Author-email: MangFu <2560782597@qq.com>
Requires-Python: >=3.6.1
Classifier: License :: OSI Approved :: MIT License
Classifier: Programming Language :: Python :: 3
Requires-Dist: httpx==0.22.0
Requires-Dist: fastapi==0.75.2
Requires-Dist: uvicorn[standard]
Project-URL: Home, https://github.com/mangfu26/mfhm
